LICENSE
MANIFEST.in
README.md
requirements.txt
setup.py
brainpy/__init__.py
brainpy/errors.py
brainpy/inputs.py
brainpy/measure.py
brainpy/running.py
brainpy/analysis/__init__.py
brainpy/analysis/base.py
brainpy/analysis/bifurcation.py
brainpy/analysis/phase_plane.py
brainpy/analysis/solver.py
brainpy/analysis/stability.py
brainpy/analysis/trajectory.py
brainpy/analysis/utils.py
brainpy/backend/__init__.py
brainpy/backend/drivers/__init__.py
brainpy/backend/drivers/numba.py
brainpy/backend/drivers/tensor.py
brainpy/backend/drivers/utils.py
brainpy/backend/ops/__init__.py
brainpy/backend/ops/more_unified_ops/__init__.py
brainpy/backend/ops/more_unified_ops/jax_.py
brainpy/backend/ops/more_unified_ops/numba.py
brainpy/backend/ops/more_unified_ops/numpy_.py
brainpy/backend/ops/more_unified_ops/pytorch_.py
brainpy/backend/ops/more_unified_ops/tensorflow_.py
brainpy/backend/ops/necessary_ops/__init__.py
brainpy/backend/ops/necessary_ops/jax_.py
brainpy/backend/ops/necessary_ops/numba.py
brainpy/backend/ops/necessary_ops/numba_overload.py
brainpy/backend/ops/necessary_ops/numpy_.py
brainpy/backend/ops/necessary_ops/pytorch_.py
brainpy/backend/ops/necessary_ops/tensorflow_.py
brainpy/integrators/__init__.py
brainpy/integrators/ast_analysis.py
brainpy/integrators/constants.py
brainpy/integrators/delay_vars.py
brainpy/integrators/integrate_wrapper.py
brainpy/integrators/sympy_analysis.py
brainpy/integrators/utils.py
brainpy/integrators/dde/__init__.py
brainpy/integrators/fde/__init__.py
brainpy/integrators/ode/__init__.py
brainpy/integrators/ode/adaptive_rk_methods.py
brainpy/integrators/ode/exp_euler_method.py
brainpy/integrators/ode/general_rk_methods.py
brainpy/integrators/ode/wrapper.py
brainpy/integrators/sde/__init__.py
brainpy/integrators/sde/common.py
brainpy/integrators/sde/euler_and_milstein.py
brainpy/integrators/sde/srk_scalar.py
brainpy/integrators/sde/srk_strong.py
brainpy/simulation/__init__.py
brainpy/simulation/delays.py
brainpy/simulation/drivers.py
brainpy_simulator.egg-info/PKG-INFO
brainpy_simulator.egg-info/SOURCES.txt
brainpy_simulator.egg-info/dependency_links.txt
brainpy_simulator.egg-info/requires.txt
brainpy_simulator.egg-info/top_level.txt