Metadata-Version: 1.2
Name: brainpy-simulator
Version: 1.0.2
Summary: BrainPy: A general platform for computational neuroscience and brain-inspired computation
Home-page: https://github.com/PKU-NIP-Lab/BrainPy
Author: Chaoming Wang
Author-email: adaduo@outlook.com
License: UNKNOWN
Keywords: computational neuroscience,brain-inspired computation,dynamical systems,differential equations,numerical integration,ordinary differential equations,stochastic differential equations,delay differential equations,fractional differential equations,ODE,SDE,DDE,FDE
Platform: UNKNOWN
Classifier: Natural Language :: English
Classifier: Operating System :: OS Independent
Classifier: Programming Language :: Python
Classifier: Programming Language :: Python :: 3
Classifier: Programming Language :: Python :: 3.6
Classifier: Programming Language :: Python :: 3.7
Classifier: Programming Language :: Python :: 3.8
Classifier: Programming Language :: Python :: 3.9
Classifier: Intended Audience :: Science/Research
Classifier: License :: OSI Approved :: GNU General Public License v3 (GPLv3)
Classifier: Topic :: Scientific/Engineering :: Bio-Informatics
Classifier: Topic :: Scientific/Engineering :: Mathematics
Classifier: Topic :: Scientific/Engineering :: Artificial Intelligence
Classifier: Topic :: Software Development :: Libraries
Requires-Python: >=3.6
